README.md
okta_aws
setup.cfg
setup.py
okta_aws/__init__.py
okta_aws/__main__.py
okta_aws/exceptions.py
okta_aws/okta_aws.py
okta_aws.egg-info/PKG-INFO
okta_aws.egg-info/SOURCES.txt
okta_aws.egg-info/dependency_links.txt
okta_aws.egg-info/entry_points.txt
okta_aws.egg-info/requires.txt
okta_aws.egg-info/top_level.txt