Metadata-Version: 1.2
Name: okta-aws
Version: 0.7.0
Summary: Use the AWS API via an account using Okta
Home-page: https://github.com/chef/okta_aws
Author: Mark Harrison
Author-email: mharrison@chef.io
License: Apache-2.0
Platform: UNKNOWN
Requires-Python: >=3
